License
MANIFEST.in
README.md
changelog
setup.py
google_cl.egg-info/PKG-INFO
google_cl.egg-info/SOURCES.txt
google_cl.egg-info/dependency_links.txt
google_cl.egg-info/requires.txt
google_cl.egg-info/top_level.txt
src/google
src/googlecl/__init__.py
src/googlecl/authentication.py
src/googlecl/base.py
src/googlecl/client.py
src/googlecl/service.py
src/googlecl/blogger/__init__.py
src/googlecl/blogger/service.py
src/googlecl/calendar/__init__.py
src/googlecl/calendar/date.py
src/googlecl/calendar/date_test.py
src/googlecl/calendar/service.py
src/googlecl/config/__init__.py
src/googlecl/config/parser.py
src/googlecl/contacts/__init__.py
src/googlecl/contacts/base.py
src/googlecl/contacts/client.py
src/googlecl/contacts/service.py
src/googlecl/discovery/__init__.py
src/googlecl/discovery/authentication.py
src/googlecl/discovery/data.py
src/googlecl/discovery/docs.py
src/googlecl/discovery/output.py
src/googlecl/docs/__init__.py
src/googlecl/docs/base.py
src/googlecl/docs/client.py
src/googlecl/docs/service.py
src/googlecl/finance/__init__.py
src/googlecl/finance/service.py
src/googlecl/picasa/__init__.py
src/googlecl/picasa/service.py
src/googlecl/youtube/__init__.py
src/googlecl/youtube/service.py