Metadata-Version: 1.1
Name: google-cl
Version: 0.9.15
Summary: Use (some) Google services from the command line
Home-page: http://github.com/vinitkumar/googlecl
Author: ['Tom H. Miller', 'Vinit Kumar']
Author-email: ['tom.h.miller@gmail.com', 'vinit.kumar@changer.nl']
License: Apache Software License
Platform: UNKNOWN
Classifier: Topic :: Internet :: WWW/HTTP
Classifier: Environment :: Console
Classifier: Development Status :: 4 - Beta
Classifier: Operating System :: POSIX
Classifier: Intended Audience :: Developers
Classifier: Intended Audience :: End Users/Desktop
